<annotation>
    <video>511-20160704-12.avi</video>
    <frame>000074</frame>
    <time>2016/07/04 12:01:20</time>
    <width>352</width>
    <height>240</height>
    <weather>1</weather>
    <facing>4</facing>
    <flow>2</flow>
    <vehicle>
        <id>1</id>
        <bndbox>
            <xmax>236</xmax>
            <xmin>224</xmin>
            <ymax>104</ymax>
            <ymin>95</ymin>
        </bndbox>
        <type>2</type>
        <direction>2</direction>
        <previous>1</previous>
    </vehicle>
    <vehicle>
        <id>2</id>
        <bndbox>
            <xmax>245</xmax>
            <xmin>232</xmin>
            <ymax>98</ymax>
            <ymin>90</ymin>
        </bndbox>
        <type>3</type>
        <direction>2</direction>
        <previous>2</previous>
    </vehicle>
    <vehicle>
        <id>3</id>
        <bndbox>
            <xmax>269</xmax>
            <xmin>251</xmin>
            <ymax>113</ymax>
            <ymin>96</ymin>
        </bndbox>
        <type>2</type>
        <direction>2</direction>
        <previous>3</previous>
    </vehicle>
    <vehicle>
        <id>4</id>
        <bndbox>
            <xmax>302</xmax>
            <xmin>289</xmin>
            <ymax>102</ymax>
            <ymin>92</ymin>
        </bndbox>
        <type>3</type>
        <direction>2</direction>
        <previous>5</previous>
    </vehicle>
    <vehicle>
        <id>5</id>
        <bndbox>
            <xmax>318</xmax>
            <xmin>305</xmin>
            <ymax>109</ymax>
            <ymin>100</ymin>
        </bndbox>
        <type>1</type>
        <direction>2</direction>
        <previous>6</previous>
    </vehicle>
    <vehicle>
        <id>6</id>
        <bndbox>
            <xmax>340</xmax>
            <xmin>326</xmin>
            <ymax>230</ymax>
            <ymin>186</ymin>
        </bndbox>
        <type>10</type>
        <direction>2</direction>
        <previous>7</previous>
    </vehicle>
    <vehicle>
        <id>7</id>
        <bndbox>
            <xmax>335</xmax>
            <xmin>325</xmin>
            <ymax>175</ymax>
            <ymin>144</ymin>
        </bndbox>
        <type>10</type>
        <direction>2</direction>
        <previous>8</previous>
    </vehicle>
</annotation>
