<annotation>
    <video>170-20160430-15.avi</video>
    <frame>000057</frame>
    <time>2016/04/30 15:01:31</time>
    <width>352</width>
    <height>240</height>
    <weather>1</weather>
    <facing>1</facing>
    <flow>1</flow>
    <vehicle>
        <id>1</id>
        <bndbox>
            <xmax>87</xmax>
            <xmin>78</xmin>
            <ymax>93</ymax>
            <ymin>87</ymin>
        </bndbox>
        <type>1</type>
        <direction>1</direction>
        <previous>1</previous>
    </vehicle>
    <vehicle>
        <id>2</id>
        <bndbox>
            <xmax>103</xmax>
            <xmin>95</xmin>
            <ymax>93</ymax>
            <ymin>87</ymin>
        </bndbox>
        <type>2</type>
        <direction>1</direction>
        <previous>2</previous>
    </vehicle>
    <vehicle>
        <id>3</id>
        <bndbox>
            <xmax>186</xmax>
            <xmin>41</xmin>
            <ymax>240</ymax>
            <ymin>222</ymin>
        </bndbox>
        <type>3</type>
        <direction>3</direction>
        <previous>3</previous>
    </vehicle>
    <vehicle>
        <id>4</id>
        <bndbox>
            <xmax>353</xmax>
            <xmin>321</xmin>
            <ymax>240</ymax>
            <ymin>197</ymin>
        </bndbox>
        <type>3</type>
        <direction>3</direction>
        <previous>0</previous>
    </vehicle>
    <passengers>
        <id>1</id>
        <bndbox>
            <xmax>320</xmax>
            <xmin>44</xmin>
            <ymax>212</ymax>
            <ymin>138</ymin>
        </bndbox>
    </passengers>
    <passengers>
        <id>2</id>
        <bndbox>
            <xmax>175</xmax>
            <xmin>137</xmin>
            <ymax>136</ymax>
            <ymin>113</ymin>
        </bndbox>
    </passengers>
    <passengers>
        <id>3</id>
        <bndbox>
            <xmax>220</xmax>
            <xmin>206</xmin>
            <ymax>144</ymax>
            <ymin>113</ymin>
        </bndbox>
    </passengers>
</annotation>
