<annotation>
    <video>511-20160505-18.avi</video>
    <frame>000299</frame>
    <time>2016/05/05 18:06:15</time>
    <width>352</width>
    <height>240</height>
    <weather>2</weather>
    <facing>2</facing>
    <flow>2</flow>
    <vehicle>
        <id>1</id>
        <bndbox>
            <xmax>117</xmax>
            <xmin>113</xmin>
            <ymax>85</ymax>
            <ymin>74</ymin>
        </bndbox>
        <type>10</type>
        <direction>1</direction>
        <previous>1</previous>
    </vehicle>
    <vehicle>
        <id>2</id>
        <bndbox>
            <xmax>239</xmax>
            <xmin>195</xmin>
            <ymax>91</ymax>
            <ymin>64</ymin>
        </bndbox>
        <type>8</type>
        <direction>1</direction>
        <previous>2</previous>
    </vehicle>
    <vehicle>
        <id>3</id>
        <bndbox>
            <xmax>101</xmax>
            <xmin>90</xmin>
            <ymax>87</ymax>
            <ymin>76</ymin>
        </bndbox>
        <type>2</type>
        <direction>1</direction>
        <previous>3</previous>
    </vehicle>
    <passengers>
        <id>1</id>
        <bndbox>
            <xmax>315</xmax>
            <xmin>279</xmin>
            <ymax>240</ymax>
            <ymin>204</ymin>
        </bndbox>
    </passengers>
    <passengers>
        <id>2</id>
        <bndbox>
            <xmax>111</xmax>
            <xmin>90</xmin>
            <ymax>240</ymax>
            <ymin>218</ymin>
        </bndbox>
    </passengers>
    <passengers>
        <id>3</id>
        <bndbox>
            <xmax>182</xmax>
            <xmin>164</xmin>
            <ymax>240</ymax>
            <ymin>217</ymin>
        </bndbox>
    </passengers>
</annotation>
