<annotation>
    <video>511-20160505-18.avi</video>
    <frame>000297</frame>
    <time>2016/05/05 18:06:13</time>
    <width>352</width>
    <height>240</height>
    <weather>2</weather>
    <facing>2</facing>
    <flow>2</flow>
    <vehicle>
        <id>1</id>
        <bndbox>
            <xmax>108</xmax>
            <xmin>103</xmin>
            <ymax>94</ymax>
            <ymin>81</ymin>
        </bndbox>
        <type>10</type>
        <direction>1</direction>
        <previous>1</previous>
    </vehicle>
    <vehicle>
        <id>2</id>
        <bndbox>
            <xmax>239</xmax>
            <xmin>195</xmin>
            <ymax>92</ymax>
            <ymin>64</ymin>
        </bndbox>
        <type>8</type>
        <direction>1</direction>
        <previous>2</previous>
    </vehicle>
    <vehicle>
        <id>3</id>
        <bndbox>
            <xmax>101</xmax>
            <xmin>91</xmin>
            <ymax>86</ymax>
            <ymin>75</ymin>
        </bndbox>
        <type>2</type>
        <direction>1</direction>
        <previous>3</previous>
    </vehicle>
    <passengers>
        <id>1</id>
        <bndbox>
            <xmax>321</xmax>
            <xmin>226</xmin>
            <ymax>240</ymax>
            <ymin>196</ymin>
        </bndbox>
    </passengers>
</annotation>
