<annotation>
    <video>170-20160429-15.avi</video>
    <frame>000118</frame>
    <time>2016/04/29 15:02:33</time>
    <width>352</width>
    <height>240</height>
    <weather>1</weather>
    <facing>1</facing>
    <flow>2</flow>
    <vehicle>
        <id>1</id>
        <bndbox>
            <xmax>67</xmax>
            <xmin>60</xmin>
            <ymax>112</ymax>
            <ymin>101</ymin>
        </bndbox>
        <type>10</type>
        <direction>1</direction>
        <previous>1</previous>
    </vehicle>
    <vehicle>
        <id>2</id>
        <bndbox>
            <xmax>85</xmax>
            <xmin>71</xmin>
            <ymax>100</ymax>
            <ymin>91</ymin>
        </bndbox>
        <type>1</type>
        <direction>1</direction>
        <previous>2</previous>
    </vehicle>
    <vehicle>
        <id>3</id>
        <bndbox>
            <xmax>87</xmax>
            <xmin>75</xmin>
            <ymax>110</ymax>
            <ymin>99</ymin>
        </bndbox>
        <type>1</type>
        <direction>1</direction>
        <previous>3</previous>
    </vehicle>
    <vehicle>
        <id>4</id>
        <bndbox>
            <xmax>101</xmax>
            <xmin>79</xmin>
            <ymax>121</ymax>
            <ymin>102</ymin>
        </bndbox>
        <type>7</type>
        <direction>1</direction>
        <previous>4</previous>
    </vehicle>
    <vehicle>
        <id>5</id>
        <bndbox>
            <xmax>102</xmax>
            <xmin>75</xmin>
            <ymax>145</ymax>
            <ymin>123</ymin>
        </bndbox>
        <type>3</type>
        <direction>1</direction>
        <previous>5</previous>
    </vehicle>
    <vehicle>
        <id>6</id>
        <bndbox>
            <xmax>93</xmax>
            <xmin>88</xmin>
            <ymax>105</ymax>
            <ymin>93</ymin>
        </bndbox>
        <type>10</type>
        <direction>1</direction>
        <previous>6</previous>
    </vehicle>
    <vehicle>
        <id>7</id>
        <bndbox>
            <xmax>112</xmax>
            <xmin>98</xmin>
            <ymax>104</ymax>
            <ymin>95</ymin>
        </bndbox>
        <type>2</type>
        <direction>1</direction>
        <previous>7</previous>
    </vehicle>
    <vehicle>
        <id>8</id>
        <bndbox>
            <xmax>117</xmax>
            <xmin>101</xmin>
            <ymax>113</ymax>
            <ymin>103</ymin>
        </bndbox>
        <type>1</type>
        <direction>1</direction>
        <previous>8</previous>
    </vehicle>
    <vehicle>
        <id>9</id>
        <bndbox>
            <xmax>134</xmax>
            <xmin>110</xmin>
            <ymax>128</ymax>
            <ymin>111</ymin>
        </bndbox>
        <type>3</type>
        <direction>1</direction>
        <previous>9</previous>
    </vehicle>
    <vehicle>
        <id>10</id>
        <bndbox>
            <xmax>168</xmax>
            <xmin>130</xmin>
            <ymax>156</ymax>
            <ymin>131</ymin>
        </bndbox>
        <type>3</type>
        <direction>1</direction>
        <previous>10</previous>
    </vehicle>
    <vehicle>
        <id>11</id>
        <bndbox>
            <xmax>214</xmax>
            <xmin>154</xmin>
            <ymax>202</ymax>
            <ymin>164</ymin>
        </bndbox>
        <type>3</type>
        <direction>1</direction>
        <previous>11</previous>
    </vehicle>
    <vehicle>
        <id>12</id>
        <bndbox>
            <xmax>133</xmax>
            <xmin>117</xmin>
            <ymax>108</ymax>
            <ymin>97</ymin>
        </bndbox>
        <type>2</type>
        <direction>1</direction>
        <previous>13</previous>
    </vehicle>
    <vehicle>
        <id>13</id>
        <bndbox>
            <xmax>148</xmax>
            <xmin>129</xmin>
            <ymax>119</ymax>
            <ymin>107</ymin>
        </bndbox>
        <type>2</type>
        <direction>1</direction>
        <previous>14</previous>
    </vehicle>
    <vehicle>
        <id>14</id>
        <bndbox>
            <xmax>173</xmax>
            <xmin>145</xmin>
            <ymax>130</ymax>
            <ymin>115</ymin>
        </bndbox>
        <type>1</type>
        <direction>1</direction>
        <previous>15</previous>
    </vehicle>
    <vehicle>
        <id>15</id>
        <bndbox>
            <xmax>222</xmax>
            <xmin>180</xmin>
            <ymax>160</ymax>
            <ymin>136</ymin>
        </bndbox>
        <type>1</type>
        <direction>1</direction>
        <previous>16</previous>
    </vehicle>
    <vehicle>
        <id>16</id>
        <bndbox>
            <xmax>285</xmax>
            <xmin>208</xmin>
            <ymax>209</ymax>
            <ymin>169</ymin>
        </bndbox>
        <type>2</type>
        <direction>1</direction>
        <previous>17</previous>
    </vehicle>
    <vehicle>
        <id>17</id>
        <bndbox>
            <xmax>186</xmax>
            <xmin>144</xmin>
            <ymax>117</ymax>
            <ymin>90</ymin>
        </bndbox>
        <type>9</type>
        <direction>1</direction>
        <previous>18</previous>
    </vehicle>
</annotation>
