<annotation>
    <video>572-20160223-12.avi</video>
    <frame>000181</frame>
    <time>2016/02/23 12:39:22</time>
    <width>352</width>
    <height>240</height>
    <weather>3</weather>
    <facing>1</facing>
    <flow>2</flow>
    <vehicle>
        <id>1</id>
        <bndbox>
            <xmax>74</xmax>
            <xmin>65</xmin>
            <ymax>131</ymax>
            <ymin>124</ymin>
        </bndbox>
        <type>3</type>
        <direction>2</direction>
        <previous>1</previous>
    </vehicle>
    <vehicle>
        <id>2</id>
        <bndbox>
            <xmax>58</xmax>
            <xmin>25</xmin>
            <ymax>204</ymax>
            <ymin>181</ymin>
        </bndbox>
        <type>3</type>
        <direction>2</direction>
        <previous>0</previous>
    </vehicle>
    <vehicle>
        <id>3</id>
        <bndbox>
            <xmax>86</xmax>
            <xmin>64</xmin>
            <ymax>171</ymax>
            <ymin>153</ymin>
        </bndbox>
        <type>3</type>
        <direction>2</direction>
        <previous>0</previous>
    </vehicle>
    <vehicle>
        <id>4</id>
        <bndbox>
            <xmax>111</xmax>
            <xmin>75</xmin>
            <ymax>220</ymax>
            <ymin>190</ymin>
        </bndbox>
        <type>3</type>
        <direction>2</direction>
        <previous>0</previous>
    </vehicle>
    <vehicle>
        <id>5</id>
        <bndbox>
            <xmax>124</xmax>
            <xmin>107</xmin>
            <ymax>148</ymax>
            <ymin>132</ymin>
        </bndbox>
        <type>5</type>
        <direction>2</direction>
        <previous>0</previous>
    </vehicle>
    <vehicle>
        <id>6</id>
        <bndbox>
            <xmax>243</xmax>
            <xmin>196</xmin>
            <ymax>235</ymax>
            <ymin>203</ymin>
        </bndbox>
        <type>3</type>
        <direction>1</direction>
        <previous>0</previous>
    </vehicle>
    <vehicle>
        <id>7</id>
        <bndbox>
            <xmax>205</xmax>
            <xmin>186</xmin>
            <ymax>140</ymax>
            <ymin>126</ymin>
        </bndbox>
        <type>5</type>
        <direction>1</direction>
        <previous>0</previous>
    </vehicle>
</annotation>
