<annotation>
    <video>173-20160429-15.avi</video>
    <frame>000190</frame>
    <time>2016/04/29 15:04:06</time>
    <width>352</width>
    <height>240</height>
    <weather>1</weather>
    <facing>1</facing>
    <flow>2</flow>
    <vehicle>
        <id>1</id>
        <bndbox>
            <xmax>161</xmax>
            <xmin>147</xmin>
            <ymax>65</ymax>
            <ymin>53</ymin>
        </bndbox>
        <type>3</type>
        <direction>2</direction>
        <previous>1</previous>
    </vehicle>
    <vehicle>
        <id>2</id>
        <bndbox>
            <xmax>176</xmax>
            <xmin>164</xmin>
            <ymax>71</ymax>
            <ymin>63</ymin>
        </bndbox>
        <type>2</type>
        <direction>2</direction>
        <previous>2</previous>
    </vehicle>
    <vehicle>
        <id>3</id>
        <bndbox>
            <xmax>208</xmax>
            <xmin>181</xmin>
            <ymax>99</ymax>
            <ymin>76</ymin>
        </bndbox>
        <type>2</type>
        <direction>2</direction>
        <previous>3</previous>
    </vehicle>
    <vehicle>
        <id>4</id>
        <bndbox>
            <xmax>75</xmax>
            <xmin>56</xmin>
            <ymax>124</ymax>
            <ymin>96</ymin>
        </bndbox>
        <type>10</type>
        <direction>2</direction>
        <previous>4</previous>
    </vehicle>
    <vehicle>
        <id>5</id>
        <bndbox>
            <xmax>271</xmax>
            <xmin>251</xmin>
            <ymax>129</ymax>
            <ymin>103</ymin>
        </bndbox>
        <type>10</type>
        <direction>6</direction>
        <previous>5</previous>
    </vehicle>
    <vehicle>
        <id>6</id>
        <bndbox>
            <xmax>345</xmax>
            <xmin>314</xmin>
            <ymax>150</ymax>
            <ymin>116</ymin>
        </bndbox>
        <type>10</type>
        <direction>1</direction>
        <previous>0</previous>
    </vehicle>
    <vehicle>
        <id>7</id>
        <bndbox>
            <xmax>133</xmax>
            <xmin>121</xmin>
            <ymax>68</ymax>
            <ymin>58</ymin>
        </bndbox>
        <type>7</type>
        <direction>2</direction>
        <previous>6</previous>
    </vehicle>
    <passengers>
        <id>1</id>
        <bndbox>
            <xmax>255</xmax>
            <xmin>243</xmin>
            <ymax>109</ymax>
            <ymin>89</ymin>
        </bndbox>
    </passengers>
    <passengers>
        <id>2</id>
        <bndbox>
            <xmax>95</xmax>
            <xmin>82</xmin>
            <ymax>137</ymax>
            <ymin>111</ymin>
        </bndbox>
    </passengers>
</annotation>
