<annotation>
    <video>170-20160505-18.avi</video>
    <frame>000125</frame>
    <time>2016/05/05 18:02:39</time>
    <width>352</width>
    <height>240</height>
    <weather>1</weather>
    <facing>1</facing>
    <flow>1</flow>
    <vehicle>
        <id>1</id>
        <bndbox>
            <xmax>73</xmax>
            <xmin>1</xmin>
            <ymax>161</ymax>
            <ymin>120</ymin>
        </bndbox>
        <type>1</type>
        <direction>1</direction>
        <previous>1</previous>
    </vehicle>
    <vehicle>
        <id>2</id>
        <bndbox>
            <xmax>12</xmax>
            <xmin>0</xmin>
            <ymax>192</ymax>
            <ymin>156</ymin>
        </bndbox>
        <type>3</type>
        <direction>1</direction>
        <previous>2</previous>
    </vehicle>
    <vehicle>
        <id>3</id>
        <bndbox>
            <xmax>89</xmax>
            <xmin>46</xmin>
            <ymax>106</ymax>
            <ymin>82</ymin>
        </bndbox>
        <type>3</type>
        <direction>1</direction>
        <previous>5</previous>
    </vehicle>
    <vehicle>
        <id>4</id>
        <bndbox>
            <xmax>47</xmax>
            <xmin>19</xmin>
            <ymax>83</ymax>
            <ymin>68</ymin>
        </bndbox>
        <type>3</type>
        <direction>1</direction>
        <previous>6</previous>
    </vehicle>
    <vehicle>
        <id>5</id>
        <bndbox>
            <xmax>68</xmax>
            <xmin>15</xmin>
            <ymax>125</ymax>
            <ymin>97</ymin>
        </bndbox>
        <type>1</type>
        <direction>1</direction>
        <previous>4</previous>
    </vehicle>
    <passengers>
        <id>1</id>
        <bndbox>
            <xmax>190</xmax>
            <xmin>172</xmin>
            <ymax>189</ymax>
            <ymin>147</ymin>
        </bndbox>
    </passengers>
    <passengers>
        <id>2</id>
        <bndbox>
            <xmax>155</xmax>
            <xmin>141</xmin>
            <ymax>144</ymax>
            <ymin>115</ymin>
        </bndbox>
    </passengers>
    <passengers>
        <id>3</id>
        <bndbox>
            <xmax>339</xmax>
            <xmin>323</xmin>
            <ymax>159</ymax>
            <ymin>122</ymin>
        </bndbox>
    </passengers>
</annotation>
