<annotation>
    <video>[Cam253]-2016_4_29_7h_150f.avi</video>
    <frame>000076</frame>
    <time>2016/04/29 07:01:43</time>
    <width>352</width>
    <height>240</height>
    <weather>1</weather>
    <facing>1</facing>
    <flow>2</flow>
    <vehicle>
        <id>1</id>
        <bndbox>
            <xmax>63</xmax>
            <xmin>56</xmin>
            <ymax>108</ymax>
            <ymin>105</ymin>
        </bndbox>
        <type>2</type>
        <direction>8</direction>
        <previous>1</previous>
    </vehicle>
    <vehicle>
        <id>2</id>
        <bndbox>
            <xmax>84</xmax>
            <xmin>73</xmin>
            <ymax>115</ymax>
            <ymin>104</ymin>
        </bndbox>
        <type>3</type>
        <direction>8</direction>
        <previous>3</previous>
    </vehicle>
    <vehicle>
        <id>3</id>
        <bndbox>
            <xmax>177</xmax>
            <xmin>144</xmin>
            <ymax>158</ymax>
            <ymin>139</ymin>
        </bndbox>
        <type>2</type>
        <direction>8</direction>
        <previous>2</previous>
    </vehicle>
    <vehicle>
        <id>4</id>
        <bndbox>
            <xmax>108</xmax>
            <xmin>97</xmin>
            <ymax>117</ymax>
            <ymin>108</ymin>
        </bndbox>
        <type>3</type>
        <direction>8</direction>
        <previous>4</previous>
    </vehicle>
    <vehicle>
        <id>5</id>
        <bndbox>
            <xmax>204</xmax>
            <xmin>179</xmin>
            <ymax>140</ymax>
            <ymin>126</ymin>
        </bndbox>
        <type>2</type>
        <direction>5</direction>
        <previous>0</previous>
    </vehicle>
    <vehicle>
        <id>6</id>
        <bndbox>
            <xmax>151</xmax>
            <xmin>138</xmin>
            <ymax>114</ymax>
            <ymin>106</ymin>
        </bndbox>
        <type>2</type>
        <direction>5</direction>
        <previous>6</previous>
    </vehicle>
    <vehicle>
        <id>7</id>
        <bndbox>
            <xmax>176</xmax>
            <xmin>158</xmin>
            <ymax>115</ymax>
            <ymin>107</ymin>
        </bndbox>
        <type>2</type>
        <direction>5</direction>
        <previous>5</previous>
    </vehicle>
    <vehicle>
        <id>8</id>
        <bndbox>
            <xmax>109</xmax>
            <xmin>101</xmin>
            <ymax>105</ymax>
            <ymin>100</ymin>
        </bndbox>
        <type>3</type>
        <direction>5</direction>
        <previous>7</previous>
    </vehicle>
    <vehicle>
        <id>9</id>
        <bndbox>
            <xmax>118</xmax>
            <xmin>114</xmin>
            <ymax>101</ymax>
            <ymin>96</ymin>
        </bndbox>
        <type>3</type>
        <direction>5</direction>
        <previous>8</previous>
    </vehicle>
</annotation>
