<annotation>
    <video>[Cam253]-2016_4_29_12h_150f.avi</video>
    <frame>000119</frame>
    <time>2016/04/29 12:02:32</time>
    <width>352</width>
    <height>240</height>
    <weather>1</weather>
    <facing>1</facing>
    <flow>2</flow>
    <vehicle>
        <id>1</id>
        <bndbox>
            <xmax>68</xmax>
            <xmin>55</xmin>
            <ymax>87</ymax>
            <ymin>79</ymin>
        </bndbox>
        <type>2</type>
        <direction>8</direction>
        <previous>1</previous>
    </vehicle>
    <vehicle>
        <id>2</id>
        <bndbox>
            <xmax>197</xmax>
            <xmin>157</xmin>
            <ymax>164</ymax>
            <ymin>138</ymin>
        </bndbox>
        <type>2</type>
        <direction>8</direction>
        <previous>3</previous>
    </vehicle>
    <vehicle>
        <id>3</id>
        <bndbox>
            <xmax>101</xmax>
            <xmin>85</xmin>
            <ymax>95</ymax>
            <ymin>83</ymin>
        </bndbox>
        <type>3</type>
        <direction>8</direction>
        <previous>4</previous>
    </vehicle>
    <vehicle>
        <id>4</id>
        <bndbox>
            <xmax>72</xmax>
            <xmin>62</xmin>
            <ymax>71</ymax>
            <ymin>64</ymin>
        </bndbox>
        <type>3</type>
        <direction>8</direction>
        <previous>5</previous>
    </vehicle>
    <vehicle>
        <id>5</id>
        <bndbox>
            <xmax>65</xmax>
            <xmin>57</xmin>
            <ymax>67</ymax>
            <ymin>61</ymin>
        </bndbox>
        <type>7</type>
        <direction>8</direction>
        <previous>0</previous>
    </vehicle>
    <vehicle>
        <id>6</id>
        <bndbox>
            <xmax>351</xmax>
            <xmin>327</xmin>
            <ymax>236</ymax>
            <ymin>186</ymin>
        </bndbox>
        <type>3</type>
        <direction>8</direction>
        <previous>6</previous>
    </vehicle>
    <vehicle>
        <id>7</id>
        <bndbox>
            <xmax>191</xmax>
            <xmin>161</xmin>
            <ymax>124</ymax>
            <ymin>104</ymin>
        </bndbox>
        <type>3</type>
        <direction>8</direction>
        <previous>7</previous>
    </vehicle>
    <vehicle>
        <id>8</id>
        <bndbox>
            <xmax>88</xmax>
            <xmin>79</xmin>
            <ymax>72</ymax>
            <ymin>65</ymin>
        </bndbox>
        <type>2</type>
        <direction>8</direction>
        <previous>8</previous>
    </vehicle>
    <vehicle>
        <id>9</id>
        <bndbox>
            <xmax>317</xmax>
            <xmin>273</xmin>
            <ymax>148</ymax>
            <ymin>124</ymin>
        </bndbox>
        <type>2</type>
        <direction>5</direction>
        <previous>0</previous>
    </vehicle>
    <vehicle>
        <id>10</id>
        <bndbox>
            <xmax>184</xmax>
            <xmin>164</xmin>
            <ymax>96</ymax>
            <ymin>86</ymin>
        </bndbox>
        <type>2</type>
        <direction>5</direction>
        <previous>9</previous>
    </vehicle>
    <vehicle>
        <id>11</id>
        <bndbox>
            <xmax>136</xmax>
            <xmin>124</xmin>
            <ymax>79</ymax>
            <ymin>71</ymin>
        </bndbox>
        <type>3</type>
        <direction>5</direction>
        <previous>10</previous>
    </vehicle>
    <vehicle>
        <id>12</id>
        <bndbox>
            <xmax>104</xmax>
            <xmin>96</xmin>
            <ymax>68</ymax>
            <ymin>61</ymin>
        </bndbox>
        <type>3</type>
        <direction>5</direction>
        <previous>11</previous>
    </vehicle>
    <vehicle>
        <id>13</id>
        <bndbox>
            <xmax>312</xmax>
            <xmin>269</xmin>
            <ymax>122</ymax>
            <ymin>102</ymin>
        </bndbox>
        <type>2</type>
        <direction>5</direction>
        <previous>0</previous>
    </vehicle>
    <vehicle>
        <id>14</id>
        <bndbox>
            <xmax>225</xmax>
            <xmin>193</xmin>
            <ymax>98</ymax>
            <ymin>74</ymin>
        </bndbox>
        <type>5</type>
        <direction>5</direction>
        <previous>14</previous>
    </vehicle>
    <vehicle>
        <id>15</id>
        <bndbox>
            <xmax>145</xmax>
            <xmin>137</xmin>
            <ymax>74</ymax>
            <ymin>67</ymin>
        </bndbox>
        <type>2</type>
        <direction>5</direction>
        <previous>15</previous>
    </vehicle>
    <vehicle>
        <id>16</id>
        <bndbox>
            <xmax>120</xmax>
            <xmin>111</xmin>
            <ymax>66</ymax>
            <ymin>60</ymin>
        </bndbox>
        <type>2</type>
        <direction>5</direction>
        <previous>16</previous>
    </vehicle>
    <vehicle>
        <id>17</id>
        <bndbox>
            <xmax>111</xmax>
            <xmin>102</xmin>
            <ymax>65</ymax>
            <ymin>58</ymin>
        </bndbox>
        <type>2</type>
        <direction>5</direction>
        <previous>17</previous>
    </vehicle>
    <vehicle>
        <id>18</id>
        <bndbox>
            <xmax>351</xmax>
            <xmin>335</xmin>
            <ymax>129</ymax>
            <ymin>107</ymin>
        </bndbox>
        <type>2</type>
        <direction>5</direction>
        <previous>0</previous>
    </vehicle>
    <vehicle>
        <id>19</id>
        <bndbox>
            <xmax>136</xmax>
            <xmin>127</xmin>
            <ymax>67</ymax>
            <ymin>60</ymin>
        </bndbox>
        <type>3</type>
        <direction>5</direction>
        <previous>19</previous>
    </vehicle>
</annotation>
