<annotation>
    <video>511-20160429-18.avi</video>
    <frame>000295</frame>
    <time>2016/04/29 18:06:13</time>
    <width>352</width>
    <height>240</height>
    <weather>1</weather>
    <facing>2</facing>
    <flow>1</flow>
    <vehicle>
        <id>1</id>
        <bndbox>
            <xmax>65</xmax>
            <xmin>0</xmin>
            <ymax>240</ymax>
            <ymin>138</ymin>
        </bndbox>
        <type>8</type>
        <direction>1</direction>
        <previous>1</previous>
    </vehicle>
    <vehicle>
        <id>2</id>
        <bndbox>
            <xmax>97</xmax>
            <xmin>68</xmin>
            <ymax>131</ymax>
            <ymin>105</ymin>
        </bndbox>
        <type>7</type>
        <direction>1</direction>
        <previous>2</previous>
    </vehicle>
    <vehicle>
        <id>3</id>
        <bndbox>
            <xmax>113</xmax>
            <xmin>94</xmin>
            <ymax>99</ymax>
            <ymin>84</ymin>
        </bndbox>
        <type>7</type>
        <direction>1</direction>
        <previous>3</previous>
    </vehicle>
    <vehicle>
        <id>4</id>
        <bndbox>
            <xmax>120</xmax>
            <xmin>108</xmin>
            <ymax>89</ymax>
            <ymin>77</ymin>
        </bndbox>
        <type>3</type>
        <direction>1</direction>
        <previous>4</previous>
    </vehicle>
    <vehicle>
        <id>5</id>
        <bndbox>
            <xmax>218</xmax>
            <xmin>203</xmin>
            <ymax>84</ymax>
            <ymin>75</ymin>
        </bndbox>
        <type>3</type>
        <direction>1</direction>
        <previous>5</previous>
    </vehicle>
    <passengers>
        <id>1</id>
        <bndbox>
            <xmax>202</xmax>
            <xmin>159</xmin>
            <ymax>81</ymax>
            <ymin>71</ymin>
        </bndbox>
    </passengers>
    <passengers>
        <id>2</id>
        <bndbox>
            <xmax>105</xmax>
            <xmin>92</xmin>
            <ymax>140</ymax>
            <ymin>112</ymin>
        </bndbox>
    </passengers>
    <passengers>
        <id>3</id>
        <bndbox>
            <xmax>257</xmax>
            <xmin>247</xmin>
            <ymax>104</ymax>
            <ymin>88</ymin>
        </bndbox>
    </passengers>
    <passengers>
        <id>4</id>
        <bndbox>
            <xmax>229</xmax>
            <xmin>205</xmin>
            <ymax>239</ymax>
            <ymin>219</ymin>
        </bndbox>
    </passengers>
</annotation>
