<annotation>
    <video>173-20160503-07.avi</video>
    <frame>000001</frame>
    <time>2016/05/03 07:54:33</time>
    <width>352</width>
    <height>240</height>
    <weather>3</weather>
    <facing>1</facing>
    <flow>1</flow>
    <vehicle>
        <id>1</id>
        <bndbox>
            <xmax>96</xmax>
            <xmin>61</xmin>
            <ymax>110</ymax>
            <ymin>67</ymin>
        </bndbox>
        <type>8</type>
        <direction>2</direction>
        <previous>0</previous>
    </vehicle>
    <vehicle>
        <id>2</id>
        <bndbox>
            <xmax>106</xmax>
            <xmin>90</xmin>
            <ymax>88</ymax>
            <ymin>68</ymin>
        </bndbox>
        <type>2</type>
        <direction>2</direction>
        <previous>0</previous>
    </vehicle>
    <vehicle>
        <id>3</id>
        <bndbox>
            <xmax>142</xmax>
            <xmin>108</xmin>
            <ymax>100</ymax>
            <ymin>62</ymin>
        </bndbox>
        <type>4</type>
        <direction>2</direction>
        <previous>0</previous>
    </vehicle>
    <vehicle>
        <id>4</id>
        <bndbox>
            <xmax>167</xmax>
            <xmin>145</xmin>
            <ymax>96</ymax>
            <ymin>79</ymin>
        </bndbox>
        <type>2</type>
        <direction>2</direction>
        <previous>0</previous>
    </vehicle>
    <vehicle>
        <id>5</id>
        <bndbox>
            <xmax>150</xmax>
            <xmin>135</xmin>
            <ymax>81</ymax>
            <ymin>68</ymin>
        </bndbox>
        <type>1</type>
        <direction>2</direction>
        <previous>0</previous>
    </vehicle>
    <vehicle>
        <id>6</id>
        <bndbox>
            <xmax>351</xmax>
            <xmin>248</xmin>
            <ymax>149</ymax>
            <ymin>76</ymin>
        </bndbox>
        <type>8</type>
        <direction>8</direction>
        <previous>0</previous>
    </vehicle>
    <vehicle>
        <id>7</id>
        <bndbox>
            <xmax>229</xmax>
            <xmin>194</xmin>
            <ymax>108</ymax>
            <ymin>86</ymin>
        </bndbox>
        <type>1</type>
        <direction>2</direction>
        <previous>0</previous>
    </vehicle>
    <vehicle>
        <id>8</id>
        <bndbox>
            <xmax>192</xmax>
            <xmin>167</xmin>
            <ymax>93</ymax>
            <ymin>76</ymin>
        </bndbox>
        <type>2</type>
        <direction>2</direction>
        <previous>0</previous>
    </vehicle>
    <vehicle>
        <id>9</id>
        <bndbox>
            <xmax>221</xmax>
            <xmin>191</xmin>
            <ymax>86</ymax>
            <ymin>66</ymin>
        </bndbox>
        <type>7</type>
        <direction>2</direction>
        <previous>0</previous>
    </vehicle>
    <vehicle>
        <id>10</id>
        <bndbox>
            <xmax>179</xmax>
            <xmin>165</xmin>
            <ymax>72</ymax>
            <ymin>61</ymin>
        </bndbox>
        <type>3</type>
        <direction>2</direction>
        <previous>0</previous>
    </vehicle>
    <vehicle>
        <id>11</id>
        <bndbox>
            <xmax>169</xmax>
            <xmin>155</xmin>
            <ymax>69</ymax>
            <ymin>58</ymin>
        </bndbox>
        <type>3</type>
        <direction>2</direction>
        <previous>0</previous>
    </vehicle>
    <vehicle>
        <id>12</id>
        <bndbox>
            <xmax>159</xmax>
            <xmin>148</xmin>
            <ymax>65</ymax>
            <ymin>56</ymin>
        </bndbox>
        <type>3</type>
        <direction>2</direction>
        <previous>0</previous>
    </vehicle>
    <vehicle>
        <id>13</id>
        <bndbox>
            <xmax>351</xmax>
            <xmin>278</xmin>
            <ymax>240</ymax>
            <ymin>192</ymin>
        </bndbox>
        <type>2</type>
        <direction>2</direction>
        <previous>0</previous>
    </vehicle>
    <vehicle>
        <id>14</id>
        <bndbox>
            <xmax>201</xmax>
            <xmin>200</xmin>
            <ymax>189</ymax>
            <ymin>186</ymin>
        </bndbox>
        <type>3</type>
        <direction>2</direction>
        <previous>0</previous>
    </vehicle>
</annotation>
