<annotation>
    <video>403-20160430-18.avi</video>
    <frame>000235</frame>
    <time>2016/04/30 18:04:37</time>
    <width>352</width>
    <height>240</height>
    <weather>1</weather>
    <facing>1</facing>
    <flow>1</flow>
    <vehicle>
        <id>1</id>
        <bndbox>
            <xmax>92</xmax>
            <xmin>80</xmin>
            <ymax>54</ymax>
            <ymin>47</ymin>
        </bndbox>
        <type>2</type>
        <direction>2</direction>
        <previous>2</previous>
    </vehicle>
    <vehicle>
        <id>2</id>
        <bndbox>
            <xmax>102</xmax>
            <xmin>95</xmin>
            <ymax>49</ymax>
            <ymin>45</ymin>
        </bndbox>
        <type>3</type>
        <direction>2</direction>
        <previous>0</previous>
    </vehicle>
    <vehicle>
        <id>3</id>
        <bndbox>
            <xmax>105</xmax>
            <xmin>92</xmin>
            <ymax>57</ymax>
            <ymin>52</ymin>
        </bndbox>
        <type>2</type>
        <direction>2</direction>
        <previous>1</previous>
    </vehicle>
    <vehicle>
        <id>4</id>
        <bndbox>
            <xmax>114</xmax>
            <xmin>96</xmin>
            <ymax>70</ymax>
            <ymin>57</ymin>
        </bndbox>
        <type>2</type>
        <direction>2</direction>
        <previous>4</previous>
    </vehicle>
    <vehicle>
        <id>5</id>
        <bndbox>
            <xmax>118</xmax>
            <xmin>108</xmin>
            <ymax>54</ymax>
            <ymin>45</ymin>
        </bndbox>
        <type>1</type>
        <direction>2</direction>
        <previous>5</previous>
    </vehicle>
    <vehicle>
        <id>6</id>
        <bndbox>
            <xmax>84</xmax>
            <xmin>69</xmin>
            <ymax>68</ymax>
            <ymin>56</ymin>
        </bndbox>
        <type>1</type>
        <direction>2</direction>
        <previous>3</previous>
    </vehicle>
    <vehicle>
        <id>7</id>
        <bndbox>
            <xmax>147</xmax>
            <xmin>115</xmin>
            <ymax>94</ymax>
            <ymin>73</ymin>
        </bndbox>
        <type>2</type>
        <direction>2</direction>
        <previous>6</previous>
    </vehicle>
    <vehicle>
        <id>8</id>
        <bndbox>
            <xmax>159</xmax>
            <xmin>142</xmin>
            <ymax>54</ymax>
            <ymin>45</ymin>
        </bndbox>
        <type>3</type>
        <direction>2</direction>
        <previous>7</previous>
    </vehicle>
    <vehicle>
        <id>9</id>
        <bndbox>
            <xmax>169</xmax>
            <xmin>143</xmin>
            <ymax>73</ymax>
            <ymin>55</ymin>
        </bndbox>
        <type>3</type>
        <direction>2</direction>
        <previous>8</previous>
    </vehicle>
    <passengers>
        <id>1</id>
        <bndbox>
            <xmax>87</xmax>
            <xmin>74</xmin>
            <ymax>147</ymax>
            <ymin>110</ymin>
        </bndbox>
    </passengers>
</annotation>
