<annotation>
    <video>[Cam253]-2016_4_30_15h_150f.avi</video>
    <frame>000067</frame>
    <time>2016/04/30 15:01:40</time>
    <width>352</width>
    <height>240</height>
    <weather>1</weather>
    <facing>1</facing>
    <flow>2</flow>
    <vehicle>
        <id>1</id>
        <bndbox>
            <xmax>151</xmax>
            <xmin>141</xmin>
            <ymax>108</ymax>
            <ymin>100</ymin>
        </bndbox>
        <type>3</type>
        <direction>8</direction>
        <previous>1</previous>
    </vehicle>
    <vehicle>
        <id>2</id>
        <bndbox>
            <xmax>178</xmax>
            <xmin>165</xmin>
            <ymax>121</ymax>
            <ymin>112</ymin>
        </bndbox>
        <type>2</type>
        <direction>8</direction>
        <previous>2</previous>
    </vehicle>
    <vehicle>
        <id>3</id>
        <bndbox>
            <xmax>164</xmax>
            <xmin>155</xmin>
            <ymax>107</ymax>
            <ymin>101</ymin>
        </bndbox>
        <type>3</type>
        <direction>8</direction>
        <previous>3</previous>
    </vehicle>
    <vehicle>
        <id>4</id>
        <bndbox>
            <xmax>281</xmax>
            <xmin>243</xmin>
            <ymax>166</ymax>
            <ymin>142</ymin>
        </bndbox>
        <type>3</type>
        <direction>8</direction>
        <previous>4</previous>
    </vehicle>
    <vehicle>
        <id>5</id>
        <bndbox>
            <xmax>201</xmax>
            <xmin>187</xmin>
            <ymax>119</ymax>
            <ymin>107</ymin>
        </bndbox>
        <type>2</type>
        <direction>8</direction>
        <previous>5</previous>
    </vehicle>
    <vehicle>
        <id>6</id>
        <bndbox>
            <xmax>165</xmax>
            <xmin>158</xmin>
            <ymax>99</ymax>
            <ymin>95</ymin>
        </bndbox>
        <type>2</type>
        <direction>8</direction>
        <previous>6</previous>
    </vehicle>
    <vehicle>
        <id>7</id>
        <bndbox>
            <xmax>216</xmax>
            <xmin>205</xmin>
            <ymax>113</ymax>
            <ymin>106</ymin>
        </bndbox>
        <type>3</type>
        <direction>5</direction>
        <previous>7</previous>
    </vehicle>
    <vehicle>
        <id>8</id>
        <bndbox>
            <xmax>191</xmax>
            <xmin>182</xmin>
            <ymax>103</ymax>
            <ymin>97</ymin>
        </bndbox>
        <type>2</type>
        <direction>5</direction>
        <previous>8</previous>
    </vehicle>
    <vehicle>
        <id>9</id>
        <bndbox>
            <xmax>172</xmax>
            <xmin>168</xmin>
            <ymax>93</ymax>
            <ymin>92</ymin>
        </bndbox>
        <type>3</type>
        <direction>5</direction>
        <previous>9</previous>
    </vehicle>
    <vehicle>
        <id>10</id>
        <bndbox>
            <xmax>328</xmax>
            <xmin>295</xmin>
            <ymax>144</ymax>
            <ymin>125</ymin>
        </bndbox>
        <type>1</type>
        <direction>5</direction>
        <previous>0</previous>
    </vehicle>
    <vehicle>
        <id>11</id>
        <bndbox>
            <xmax>276</xmax>
            <xmin>257</xmin>
            <ymax>119</ymax>
            <ymin>108</ymin>
        </bndbox>
        <type>2</type>
        <direction>5</direction>
        <previous>0</previous>
    </vehicle>
    <vehicle>
        <id>12</id>
        <bndbox>
            <xmax>228</xmax>
            <xmin>216</xmin>
            <ymax>110</ymax>
            <ymin>103</ymin>
        </bndbox>
        <type>2</type>
        <direction>5</direction>
        <previous>11</previous>
    </vehicle>
    <vehicle>
        <id>13</id>
        <bndbox>
            <xmax>200</xmax>
            <xmin>193</xmin>
            <ymax>102</ymax>
            <ymin>97</ymin>
        </bndbox>
        <type>3</type>
        <direction>5</direction>
        <previous>12</previous>
    </vehicle>
    <vehicle>
        <id>14</id>
        <bndbox>
            <xmax>187</xmax>
            <xmin>182</xmin>
            <ymax>96</ymax>
            <ymin>91</ymin>
        </bndbox>
        <type>2</type>
        <direction>5</direction>
        <previous>13</previous>
    </vehicle>
</annotation>
