<annotation>
    <video>253-20160704-07.avi</video>
    <frame>000274</frame>
    <time>2016/07/04 07:59:26</time>
    <width>352</width>
    <height>240</height>
    <weather>1</weather>
    <facing>1</facing>
    <flow>2</flow>
    <vehicle>
        <id>1</id>
        <bndbox>
            <xmax>125</xmax>
            <xmin>121</xmin>
            <ymax>84</ymax>
            <ymin>80</ymin>
        </bndbox>
        <type>3</type>
        <direction>1</direction>
        <previous>1</previous>
    </vehicle>
    <vehicle>
        <id>2</id>
        <bndbox>
            <xmax>225</xmax>
            <xmin>204</xmin>
            <ymax>112</ymax>
            <ymin>100</ymin>
        </bndbox>
        <type>2</type>
        <direction>1</direction>
        <previous>2</previous>
    </vehicle>
    <vehicle>
        <id>3</id>
        <bndbox>
            <xmax>179</xmax>
            <xmin>167</xmin>
            <ymax>98</ymax>
            <ymin>91</ymin>
        </bndbox>
        <type>1</type>
        <direction>1</direction>
        <previous>3</previous>
    </vehicle>
    <vehicle>
        <id>4</id>
        <bndbox>
            <xmax>183</xmax>
            <xmin>173</xmin>
            <ymax>94</ymax>
            <ymin>88</ymin>
        </bndbox>
        <type>3</type>
        <direction>1</direction>
        <previous>5</previous>
    </vehicle>
</annotation>
